fillit/__init__.py
fillit/__main__.py
fillit-0.1.0.dist-info/METADATA
fillit-0.1.0.dist-info/WHEEL
fillit-0.1.0.dist-info/entry_points.txt
fillit-0.1.0.dist-info/top_level.txt
fillit-0.1.0.dist-info/RECORD
